pypam/__init__.py
pypam/assign.py
pypam3/__init__.py
pypam3/assign.py
pypam3-0.1.2.dist-info/LICENCE
pypam3-0.1.2.dist-info/METADATA
pypam3-0.1.2.dist-info/WHEEL
pypam3-0.1.2.dist-info/top_level.txt
pypam3-0.1.2.dist-info/RECORD
